shibboleth_authenticator/__init__.py
shibboleth_authenticator/_compat.py
shibboleth_authenticator/config.py
shibboleth_authenticator/ext.py
shibboleth_authenticator/handlers.py
shibboleth_authenticator/utils.py
shibboleth_authenticator/version.py
shibboleth_authenticator/views.py
shibboleth_authenticator-0.1.5.dist-info/LICENSE
shibboleth_authenticator-0.1.5.dist-info/METADATA
shibboleth_authenticator-0.1.5.dist-info/WHEEL
shibboleth_authenticator-0.1.5.dist-info/entry_points.txt
shibboleth_authenticator-0.1.5.dist-info/top_level.txt
shibboleth_authenticator-0.1.5.dist-info/RECORD
