Metadata-Version: 2.1
Name: shibboleth-authenticator
Version: 0.1.5
Summary: Module for Invenio that provides authentication via Shibboleth.
Home-page: https://github.com/hzdr/shibboleth-authenticator
Author: HZDR
Author-email: t.frust@hzdr.de
License: GPLv3
Keywords: invenio shibboleth authentication
Platform: any
Classifier: Environment :: Web Environment
Classifier: Intended Audience :: Developers
Classifier: License :: OSI Approved :: GNU General Public License v3 (GPLv3)
Classifier: Operating System :: OS Independent
Classifier: Programming Language :: Python
Classifier: Topic :: Internet :: WWW/HTTP :: Dynamic Content
Classifier: Topic :: Software Development :: Libraries :: Python Modules
Classifier: Programming Language :: Python :: 2
Classifier: Programming Language :: Python :: 2.7
Classifier: Programming Language :: Python :: 3
Classifier: Programming Language :: Python :: 3.5
Classifier: Programming Language :: Python :: 3.6
Classifier: Programming Language :: Python :: Implementation :: CPython
Classifier: Development Status :: 5 - Production/Stable
Requires-Dist: Flask (>=0.11.1)
Requires-Dist: Flask-Login (>=0.3.2)
Requires-Dist: Flask-WTF (>=0.13.1)
Requires-Dist: oauthlib (!=2.0.3,!=2.0.4,!=2.0.5,<3.0.0,>=1.1.2)
Requires-Dist: python3-saml (>=1.4.0)
Requires-Dist: requests-oauthlib (<1.2.0,>=0.6.2)
Requires-Dist: uritools (>=1.0.1)
Provides-Extra: all
Requires-Dist: recommonmark (>=0.4.0) ; extra == 'all'
Requires-Dist: Sphinx (>=1.5.1) ; extra == 'all'
Requires-Dist: check-manifest (>=0.35) ; extra == 'all'
Requires-Dist: coverage (>=4.0) ; extra == 'all'
Requires-Dist: invenio-accounts (>=1.0.0) ; extra == 'all'
Requires-Dist: invenio-userprofiles (>=1.0.0) ; extra == 'all'
Requires-Dist: isort (>=4.3.3) ; extra == 'all'
Requires-Dist: mock (>=1.3.0) ; extra == 'all'
Requires-Dist: pydocstyle (>=1.1.1) ; extra == 'all'
Requires-Dist: pytest-cache (>=1.0) ; extra == 'all'
Requires-Dist: pytest-cov (>=1.8.0) ; extra == 'all'
Requires-Dist: pytest-pep8 (>=1.0.6) ; extra == 'all'
Requires-Dist: pytest (>=2.8.3) ; extra == 'all'
Requires-Dist: sphinx-rtd-theme (>=0.2.4) ; extra == 'all'
Provides-Extra: docs
Requires-Dist: recommonmark (>=0.4.0) ; extra == 'docs'
Requires-Dist: Sphinx (>=1.5.1) ; extra == 'docs'
Provides-Extra: mysql
Requires-Dist: invenio-oauthclient[mysql] (>=1.0.0) ; extra == 'mysql'
Provides-Extra: postgresql
Requires-Dist: invenio-oauthclient[postgresql] (>=1.0.0) ; extra == 'postgresql'
Provides-Extra: sqlite
Requires-Dist: invenio-oauthclient[sqlite] (>=1.0.0) ; extra == 'sqlite'
Provides-Extra: tests
Requires-Dist: check-manifest (>=0.35) ; extra == 'tests'
Requires-Dist: coverage (>=4.0) ; extra == 'tests'
Requires-Dist: invenio-accounts (>=1.0.0) ; extra == 'tests'
Requires-Dist: invenio-userprofiles (>=1.0.0) ; extra == 'tests'
Requires-Dist: isort (>=4.3.3) ; extra == 'tests'
Requires-Dist: mock (>=1.3.0) ; extra == 'tests'
Requires-Dist: pydocstyle (>=1.1.1) ; extra == 'tests'
Requires-Dist: pytest-cache (>=1.0) ; extra == 'tests'
Requires-Dist: pytest-cov (>=1.8.0) ; extra == 'tests'
Requires-Dist: pytest-pep8 (>=1.0.6) ; extra == 'tests'
Requires-Dist: pytest (>=2.8.3) ; extra == 'tests'
Requires-Dist: sphinx-rtd-theme (>=0.2.4) ; extra == 'tests'
